apispec_fromfile/__init__.py
apispec_fromfile/plugin.py
APISpec_fromfile-1.0.3.dist-info/AUTHORS
APISpec_fromfile-1.0.3.dist-info/LICENSE
APISpec_fromfile-1.0.3.dist-info/METADATA
APISpec_fromfile-1.0.3.dist-info/WHEEL
APISpec_fromfile-1.0.3.dist-info/top_level.txt
APISpec_fromfile-1.0.3.dist-info/RECORD
