Metadata-Version: 2.1
Name: APISpec-fromfile
Version: 1.0.3
Summary: APISpec plugin to import OpenAPI specifications from a file instead of putting YAML into docstrings
Home-page: https://github.com/ovh/python-apispec-fromfile
Author: OVHcloud
Author-email: opensource@ovhcloud.com
License: UNKNOWN
Keywords: openapi apispec
Platform: UNKNOWN
Classifier: Environment :: Plugins
Classifier: Environment :: Web Environment
Classifier: Intended Audience :: Developers
Classifier: License :: OSI Approved :: Apache Software License
Classifier: Programming Language :: Python
Classifier: Programming Language :: Python :: 3
Classifier: Topic :: Documentation
Classifier: Topic :: Internet :: WWW/HTTP
Classifier: Topic :: Software Development :: Libraries :: Python Modules
Requires-Python: >=3.6
License-File: LICENSE
License-File: AUTHORS
